<?xml version="1.0" encoding="UTF-8"?>
<!-- generated by com.composum.ai.composum.bundle.WriteSidebarPredefinedPromptsInAEMFormat - can be used for updating, too. -->
<jcr:root xmlns:sling="http://sling.apache.org/jcr/sling/1.0" xmlns:jcr="http://www.jcp.org/jcr/1.0"
          xmlns:nt="http://www.jcp.org/jcr/nt/1.0" jcr:primaryType="sling:OrderedFolder">
    <empty jcr:primaryType="nt:unstructured" sling:resourceType="nt:unstructured"
         text="---"
         value="-"></empty>
    <simplification_suggestions jcr:primaryType="nt:unstructured" sling:resourceType="nt:unstructured"
                                text="Simplification Suggestions"
                                value="Identify and print parts of the text that could be simplified or made easier to understand, and suggest alternative wording."></simplification_suggestions>
    <content_flow jcr:primaryType="nt:unstructured" sling:resourceType="nt:unstructured"
                  text="Content Flow"
                  value="Analyze the flow of the content. Does it progress logically? Is there a clear introduction, body, and conclusion?"></content_flow>
    <review jcr:primaryType="nt:unstructured" sling:resourceType="nt:unstructured"
            text="Review"
            value="Check whether there is a good text flow, and whether there are contradictions or repetitions and redundancy in the text, inconsistent style or tone and stylistic problems. Check for long and complicated sentences that could be made simpler and more understandable. Give suggestions for improvement. Be picky."></review>
    <question jcr:primaryType="nt:unstructured" sling:resourceType="nt:unstructured"
              text="Question"
              value="Please answer the following question based on the given text:
        "></question>
    <___headline_suggestions jcr:primaryType="nt:unstructured" sling:resourceType="nt:unstructured"
                             text="10 headline suggestions"
                             value="Please write 10 suggestions for a headline for the text. Print just the raw headline, no explanations and no quotes. Use a businesslike informative style."></___headline_suggestions>
    <___headline___subheading_suggestions jcr:primaryType="nt:unstructured" sling:resourceType="nt:unstructured"
                                          text="10 headline + subheading suggestions"
                                          value="Please write 10 suggestions for a headline and a subheading for the text. For each suggestion print just the raw headline and in the next line a subheading. Please no explanations and no surrounding with quotes. Use a businesslike informative style."></___headline___subheading_suggestions>
    <summary jcr:primaryType="nt:unstructured" sling:resourceType="nt:unstructured"
             text="Summary"
             value="Please provide a brief summary of the main points and themes in the text."></summary>
    <sentiment_analysis jcr:primaryType="nt:unstructured" sling:resourceType="nt:unstructured"
                        text="Sentiment Analysis"
                        value="Analyze the sentiment conveyed by the text. Is it positive, negative, or neutral? How strong is the sentiment?"></sentiment_analysis>
    <aida_content_audit jcr:primaryType="nt:unstructured" sling:resourceType="nt:unstructured"
                        text="AIDA Content Audit"
                        value="Review the provided text and suggest improvements following the AIDA model (Attention, Interest, Desire, and Action). Point out areas where attention-grabbing, interest building, desire amplification, or call-to-action might be lacking and provide suggestions to enhance each aspect."></aida_content_audit>
    <bab_content_audit jcr:primaryType="nt:unstructured" sling:resourceType="nt:unstructured"
                       text="BAB Content Audit"
                       value="Review the provided text and suggest improvements following the BAB Before-After-Bridge) model. Provide suggestions to enhance the 'Before' situation, 'After' vision, and 'Bridge' solution, making sure the reader can clearly see the transformation and the role our product/service plays in it."></bab_content_audit>
    <cta_evaluation jcr:primaryType="nt:unstructured" sling:resourceType="nt:unstructured"
                    text="CTA Evaluation"
                    value="Examine the current call-to-action (CTA) in the text. Does it compel the reader to take the desired action? Is it clear and persuasive? Are there ways to improve it? If there is no CTA, suggest one that fits the content and intended audience. Prioritize CTAs that are actionable, emotionally engaging, and concise."></cta_evaluation>
    <cta_suggestions jcr:primaryType="nt:unstructured" sling:resourceType="nt:unstructured"
                     text="CTA Suggestions"
                     value="Based on the main topic of the content, please suggest five distinct call-to-action (CTA) phrases that could motivate readers to engage further with the content or the brand. The CTAs should be clear, concise, and create a sense of urgency."></cta_suggestions>
    <content_gap_analysis jcr:primaryType="nt:unstructured" sling:resourceType="nt:unstructured"
                          text="Content Gap Analysis"
                          value="Analyze the text to identify topics or subtopics that are not covered but could be relevant and valuable to the audience. Consider what questions the reader might still have after reading the text, and what additional information or perspectives could be included to make the text more comprehensive and informative."></content_gap_analysis>
    <addressing_content_gaps jcr:primaryType="nt:unstructured" sling:resourceType="nt:unstructured"
                             text="Addressing Content Gaps"
                             value="Based on the identified content gaps, provide specific suggestions on how to fill these gaps. Include ideas for new sections, topics, or types of information that could be added to the text, as well as any changes to the text's organization or flow that could help integrate this new content."></addressing_content_gaps>
    <response_simulation jcr:primaryType="nt:unstructured" sling:resourceType="nt:unstructured"
                         text="Response simulation"
                         value="Simulate a positive, a negative and a neutral response of a reader about the provided text."></response_simulation>
    <tone_analysis jcr:primaryType="nt:unstructured" sling:resourceType="nt:unstructured"
                   text="Tone Analysis"
                   value="Analyze the tone of the text. Is it formal, informal, friendly, confrontational, enthusiastic, neutral, etc?"></tone_analysis>
    <audience_suitability jcr:primaryType="nt:unstructured" sling:resourceType="nt:unstructured"
                          text="Audience Suitability"
                          value="Given the following audience profile, evaluate whether the text is suitable, and suggest any needed improvements:
        "></audience_suitability>
    <relevance_evaluation jcr:primaryType="nt:unstructured" sling:resourceType="nt:unstructured"
                          text="Relevance Evaluation"
                          value="Evaluate whether the content of the text is relevant to the following topic or purpose:
        "></relevance_evaluation>
    <fact_check jcr:primaryType="nt:unstructured" sling:resourceType="nt:unstructured"
                text="Fact Check"
                value="Identify any factual claims in the text and indicate whether they are generally considered accurate, inaccurate, or uncertain."></fact_check>
    <proofread jcr:primaryType="nt:unstructured" sling:resourceType="nt:unstructured"
               text="Proofread"
               value="Please check the text for any spelling, grammar, or punctuation errors, typos, incorrect  sentence structure and incorrect / inappropriate word usage, run-on sentences, incorrect subject-verb agreement, missing or repeated words. In each problem report, print a the part of the sentence where the problem occurs and how that part of the sentence would be improved. Sort the reported problems by severity."></proofread>
    <keyword_density jcr:primaryType="nt:unstructured" sling:resourceType="nt:unstructured"
                     text="Keyword Density"
                     value="Identify the most frequently used words or phrases in the text, excluding common function words."></keyword_density>
</jcr:root>
